{
    "name": "custom",
    "startup": {
        "name": "Startup",
        "start_time": 0,
        "duration": 5,
        "start_position": 0,
        "end_position": 0,
        "start_altitude": 0,
        "end_altitude": 0,
        "energy": 10,
        "state": {
            "horizontal_speed": 0,
            "vertical_speed": 0,
            "power": 10,
            "C_L": 0
        }
    },
    "takeoff": {
        "name": "Takeoff",
        "start_time": 5,
        "duration": 10,
        "start_position": 0,
        "end_position": 100,
        "start_altitude": 0,
        "end_altitude": 50,
        "energy": 100,
        "state": {
            "horizontal_speed": 10,
            "vertical_speed": 5,
            "power": 100,
            "C_L": 0.5
        }
    },
    "vertical_climb": null,
    "transition1": null,
    "climb": null,
    "cruise": null,
    "descent": null,
    "transition2": null,
    "hover": null,
    "vertical_descent": null,
    "landing": null
}